openapi3/__init__.py
openapi3/__main__.py
openapi3/components.py
openapi3/errors.py
openapi3/example.py
openapi3/general.py
openapi3/info.py
openapi3/object_base.py
openapi3/openapi.py
openapi3/paths.py
openapi3/schemas.py
openapi3/security.py
openapi3/servers.py
openapi3/tag.py
openapi3-1.8.2.dist-info/LICENSE
openapi3-1.8.2.dist-info/METADATA
openapi3-1.8.2.dist-info/WHEEL
openapi3-1.8.2.dist-info/top_level.txt
openapi3-1.8.2.dist-info/RECORD
