Metadata-Version: 2.1
Name: openapi3
Version: 1.8.2
Summary: Client and Validator of OpenAPI 3 Specifications
Home-page: https://github.com/dorthu/openapi3
Author: dorthu
License: BSD 3-Clause License
Platform: UNKNOWN
Provides-Extra: test
